{"nodes": {"User": "0", "watermelons": "1", "July 04, 2026": "2", "painting watermelons": "3", "a painting": "4", "User started working on a painting": "5", "July 05, 2026": "6", "how to bake a cake": "7", "chocolates": "8", "User likes chocolates": "9", "Kung Fu Panda": "10", "User has favourite movie": "11", "User finds Kung Fu Panda inspirational": "12", "music": "13", "User is fond of music": "14"}, "edges": [{"source": "0", "target": "1", "label": "likes", "subj": "User", "obj": "watermelons"}, {"source": "0", "target": "2", "label": "happened_on", "subj": "User", "obj": "July 04, 2026"}, {"source": "3", "target": "2", "label": "occurred_on", "subj": "painting watermelons", "obj": "July 04, 2026"}, {"source": "0", "target": "4", "label": "started_working_on", "subj": "User", "obj": "a painting"}, {"source": "5", "target": "2", "label": "happened_on", "subj": "User started working on a painting", "obj": "July 04, 2026"}, {"source": "0", "target": "6", "label": "learned_on", "subj": "User", "obj": "July 05, 2026"}, {"source": "0", "target": "7", "label": "learned", "subj": "User", "obj": "how to bake a cake"}, {"source": "7", "target": "6", "label": "happened_on", "subj": "how to bake a cake", "obj": "July 05, 2026"}, {"source": "0", "target": "8", "label": "likes", "subj": "User", "obj": "chocolates"}, {"source": "9", "target": "6", "label": "mentioned_date", "subj": "User likes chocolates", "obj": "July 05, 2026"}, {"source": "0", "target": "6", "label": "mentioned_date", "subj": "User", "obj": "July 05, 2026"}, {"source": "0", "target": "10", "label": "has_favourite_movie", "subj": "User", "obj": "Kung Fu Panda"}, {"source": "11", "target": "6", "label": "happened_on", "subj": "User has favourite movie", "obj": "July 05, 2026"}, {"source": "12", "target": "6", "label": "happened_on", "subj": "User finds Kung Fu Panda inspirational", "obj": "July 05, 2026"}, {"source": "0", "target": "10", "label": "finds_inspirational", "subj": "User", "obj": "Kung Fu Panda"}, {"source": "0", "target": "13", "label": "is_fond_of", "subj": "User", "obj": "music"}, {"source": "14", "target": "6", "label": "happened_on", "subj": "User is fond of music", "obj": "July 05, 2026"}]}